index_parser/__init__.py
index_parser/__main__.py
index_parser/app.py
index_parser/cli.py
index_parser/data.py
index_parser/static/index.html
index_parser-0.0.1.dev0.dist-info/LICENSE.txt
index_parser-0.0.1.dev0.dist-info/METADATA
index_parser-0.0.1.dev0.dist-info/WHEEL
index_parser-0.0.1.dev0.dist-info/top_level.txt
index_parser-0.0.1.dev0.dist-info/RECORD
